[
  {
    "ContainingType": "FlightSearchEngine.Controllers.FlightsController",
    "Method": "SearchAirports",
    "RelativePath": "api/Flights/airports",
    "HttpMethod": "GET",
    "IsController": true,
    "Order": 0,
    "Parameters": [
      {
        "Name": "keyword",
        "Type": "System.String",
        "IsRequired": false
      }
    ],
    "ReturnTypes": [
      {
        "Type": "System.Collections.Generic.List\u00601[[FlightSearchEngine.Models.Airport, FlightSearchEngine, Version=1.0.0.0, Culture=neutral, PublicKeyToken=null]]",
        "MediaTypes": [
          "text/plain",
          "application/json",
          "text/json"
        ],
        "StatusCode": 200
      }
    ]
  },
  {
    "ContainingType": "FlightSearchEngine.Controllers.FlightsController",
    "Method": "GetTravelClasses",
    "RelativePath": "api/Flights/classes",
    "HttpMethod": "GET",
    "IsController": true,
    "Order": 0,
    "Parameters": [],
    "ReturnTypes": [
      {
        "Type": "System.Collections.Generic.List\u00601[[System.Object, System.Private.CoreLib, Version=10.0.0.0, Culture=neutral, PublicKeyToken=7cec85d7bea7798e]]",
        "MediaTypes": [
          "text/plain",
          "application/json",
          "text/json"
        ],
        "StatusCode": 200
      }
    ]
  },
  {
    "ContainingType": "FlightSearchEngine.Controllers.FlightsController",
    "Method": "SearchFlights",
    "RelativePath": "api/Flights/search",
    "HttpMethod": "GET",
    "IsController": true,
    "Order": 0,
    "Parameters": [
      {
        "Name": "origin",
        "Type": "System.String",
        "IsRequired": false
      },
      {
        "Name": "destination",
        "Type": "System.String",
        "IsRequired": false
      },
      {
        "Name": "departureDate",
        "Type": "System.DateTime",
        "IsRequired": false
      },
      {
        "Name": "returnDate",
        "Type": "System.Nullable\u00601[[System.DateTime, System.Private.CoreLib, Version=10.0.0.0, Culture=neutral, PublicKeyToken=7cec85d7bea7798e]]",
        "IsRequired": false
      },
      {
        "Name": "adults",
        "Type": "System.Int32",
        "IsRequired": false
      },
      {
        "Name": "children",
        "Type": "System.Int32",
        "IsRequired": false
      },
      {
        "Name": "infants",
        "Type": "System.Int32",
        "IsRequired": false
      },
      {
        "Name": "travelClass",
        "Type": "System.String",
        "IsRequired": false
      },
      {
        "Name": "sortBy",
        "Type": "System.String",
        "IsRequired": false
      },
      {
        "Name": "directOnly",
        "Type": "System.Nullable\u00601[[System.Boolean, System.Private.CoreLib, Version=10.0.0.0, Culture=neutral, PublicKeyToken=7cec85d7bea7798e]]",
        "IsRequired": false
      },
      {
        "Name": "maxStops",
        "Type": "System.Nullable\u00601[[System.Int32, System.Private.CoreLib, Version=10.0.0.0, Culture=neutral, PublicKeyToken=7cec85d7bea7798e]]",
        "IsRequired": false
      },
      {
        "Name": "departureTimeMin",
        "Type": "System.String",
        "IsRequired": false
      },
      {
        "Name": "departureTimeMax",
        "Type": "System.String",
        "IsRequired": false
      }
    ],
    "ReturnTypes": [
      {
        "Type": "FlightSearchEngine.Models.FlightSearchResult",
        "MediaTypes": [
          "text/plain",
          "application/json",
          "text/json"
        ],
        "StatusCode": 200
      }
    ]
  },
  {
    "ContainingType": "FlightSearchEngine.Controllers.FlightsController",
    "Method": "GetSortOptions",
    "RelativePath": "api/Flights/sort-options",
    "HttpMethod": "GET",
    "IsController": true,
    "Order": 0,
    "Parameters": [],
    "ReturnTypes": [
      {
        "Type": "System.Collections.Generic.List\u00601[[System.Object, System.Private.CoreLib, Version=10.0.0.0, Culture=neutral, PublicKeyToken=7cec85d7bea7798e]]",
        "MediaTypes": [
          "text/plain",
          "application/json",
          "text/json"
        ],
        "StatusCode": 200
      }
    ]
  }
]